{
    "Ar36": {
        "error": 0.0002967088886731224, 
        "filter_outliers_dict": {
            "filter_outliers": true, 
            "iterations": 1, 
            "std_devs": 2
        }, 
        "fit": "Linear", 
        "value": 0.015037022651671592
    }, 
    "Ar37": {
        "error": 0.010251144973296841, 
        "filter_outliers_dict": {
            "filter_outliers": true, 
            "iterations": 1, 
            "std_devs": 2
        }, 
        "fit": "linear", 
        "value": 0.9200802556118209
    }, 
    "Ar38": {
        "error": 0.006212005152738178, 
        "filter_outliers_dict": {
            "filter_outliers": true, 
            "iterations": 1, 
            "std_devs": 2
        }, 
        "fit": "linear", 
        "value": 3.265472566747383
    }, 
    "Ar39": {
        "error": 0.027745135253867983, 
        "filter_outliers_dict": {
            "filter_outliers": true, 
            "iterations": 1, 
            "std_devs": 2
        }, 
        "fit": "Linear", 
        "value": 251.1436082748632
    }, 
    "Ar40": {
        "error": 0.0647886003157654, 
        "filter_outliers_dict": {
            "filter_outliers": true, 
            "iterations": 1, 
            "std_devs": 2
        }, 
        "fit": "Linear", 
        "value": 1037.1744542737508
    }, 
    "PM41": {
        "error": 0.06880993240869733, 
        "filter_outliers_dict": {
            "filter_outliers": false, 
            "iterations": 1, 
            "std_devs": 2
        }, 
        "fit": "linear", 
        "value": -0.0802418233679121
    }
}