{
    "Ar36": {
        "error": 0.00018219916736320716, 
        "filter_outliers_dict": {
            "filter_outliers": true, 
            "iterations": 1, 
            "std_devs": 2
        }, 
        "fit": "Parabolic", 
        "value": 0.004547392266008785
    }, 
    "Ar37": {
        "error": 0.0048939366519762115, 
        "filter_outliers_dict": {
            "filter_outliers": true, 
            "iterations": 1, 
            "std_devs": 2
        }, 
        "fit": "linear", 
        "value": 0.0066977943725028384
    }, 
    "Ar38": {
        "error": 0.0021420887943773984, 
        "filter_outliers_dict": {
            "filter_outliers": true, 
            "iterations": 1, 
            "std_devs": 2
        }, 
        "fit": "linear", 
        "value": -0.023810002482001238
    }, 
    "Ar39": {
        "error": 0.009243373098025845, 
        "filter_outliers_dict": {
            "filter_outliers": true, 
            "iterations": 1, 
            "std_devs": 2
        }, 
        "fit": "Parabolic", 
        "value": -0.04507350150737021
    }, 
    "Ar40": {
        "error": 0.007047718854459857, 
        "filter_outliers_dict": {
            "filter_outliers": true, 
            "iterations": 1, 
            "std_devs": 2
        }, 
        "fit": "Parabolic", 
        "value": 0.3565308655409213
    }, 
    "PM41": {
        "error": 0.061015230518531624, 
        "filter_outliers_dict": {
            "filter_outliers": false, 
            "iterations": 1, 
            "std_devs": 2
        }, 
        "fit": "linear", 
        "value": -0.19090237613913624
    }
}